py_thumbpad/__init__.py
py_thumbpad/button_pad.py
py_thumbpad/donut.py
py_thumbpad/events.py
py_thumbpad/tween.py
py_thumbpad/utils.py
py_thumbpad-1.0.5.dist-info/METADATA
py_thumbpad-1.0.5.dist-info/WHEEL
py_thumbpad-1.0.5.dist-info/entry_points.txt
py_thumbpad-1.0.5.dist-info/top_level.txt
py_thumbpad-1.0.5.dist-info/RECORD
