Metadata-Version: 2.1
Name: py-thumbpad
Version: 1.0.5
Summary: A virtual thumb pad for directional input, featuring a central donut shape and a movable button pad.
Home-page: https://github.com/kerodekroma/py-thumbpad
Author: kerodekroma
Author-email: kerodekroma@gmail.com
License: UNKNOWN
Platform: UNKNOWN
Classifier: Programming Language :: Python :: 3
Classifier: License :: OSI Approved :: MIT License
Classifier: Operating System :: OS Independent
Requires-Python: >=3.6
Requires-Dist: pygame (>=2.0.0)
